mdformat_shfmt/__init__.py
mdformat_shfmt-0.2.0.dist-info/LICENSE
mdformat_shfmt-0.2.0.dist-info/METADATA
mdformat_shfmt-0.2.0.dist-info/WHEEL
mdformat_shfmt-0.2.0.dist-info/entry_points.txt
mdformat_shfmt-0.2.0.dist-info/RECORD
