Metadata-Version: 2.1
Name: mdformat-shfmt
Version: 0.2.0
Summary: Mdformat plugin to format shell code blocks
Home-page: https://github.com/hukkin/mdformat-shfmt
License: MIT
Keywords: mdformat,markdown,commonmark,formatter,bash,shell
Author: Taneli Hukkinen
Author-email: hukkin@users.noreply.github.com
Requires-Python: >=3.9
Classifier: License :: OSI Approved :: MIT License
Classifier: Programming Language :: Python :: 3
Classifier: Programming Language :: Python :: 3.9
Classifier: Programming Language :: Python :: 3.10
Classifier: Programming Language :: Python :: 3.11
Classifier: Programming Language :: Python :: 3.12
Classifier: Programming Language :: Python :: 3.13
Classifier: Topic :: Documentation
Classifier: Topic :: Text Processing :: Markup
Requires-Dist: mdformat (>=0.3.5)
Project-URL: Repository, https://github.com/hukkin/mdformat-shfmt
